AUTHORS
CHANGES.rst
LICENSE
MANIFEST.in
README.rst
TODO.md
debian8-dist.sh
setup.py
ca/__init__.py
ca/grid/__init__.py
ca/grid/grid2d.py
ca/gui/__init__.py
ca/gui/tk.py
ca/rules/__init__.py
ca/rules/conway.py
cellular_automata.egg-info/PKG-INFO
cellular_automata.egg-info/SOURCES.txt
cellular_automata.egg-info/dependency_links.txt
cellular_automata.egg-info/entry_points.txt
cellular_automata.egg-info/top_level.txt
tests/test_rules.py