Metadata-Version: 1.1
Name: cellular-automata
Version: 0.1.dev1
Summary: A lightweight cellular automata framework
Home-page: http://www.jdhp.org/
Author: Jeremie DECOCK
Author-email: jd.jdhp@gmail.com
License: UNKNOWN
Download-URL: http://www.jdhp.org/
Platform: UNKNOWN
Classifier: Development Status :: 4 - Beta
Classifier: Intended Audience :: Science/Research
Classifier: License :: OSI Approved :: MIT License
Classifier: Natural Language :: English
Classifier: Operating System :: OS Independent
Classifier: Programming Language :: Python :: 3
Classifier: Topic :: Scientific/Engineering :: Artificial Life
Classifier: Topic :: Software Development :: Libraries
